{"elapsed":"0.787","endpoint-url":"https://www.hart.gov.uk/sites/default/files/4_The_Council/Policies_and_published_documents/Planning_policy/IFS%202020%20Jan%2021%20Final.pdf","entry-date":"2023-07-16T00:11:07.758383","request-headers":{"Accept":"*/*","Accept-Encoding":"gzip, deflate","Connection":"keep-alive","User-Agent":"DLUHC Digital Land"},"response-headers":{"Cache-Control":"max-age=1800, public","Connection":"keep-alive","Content-Language":"en","Content-Type":"text/html; charset=UTF-8","Date":"Sun, 16 Jul 2023 00:13:07 GMT","ETag":"\"1689466387\"","Expires":"Sun, 19 Nov 1978 05:00:00 GMT","Last-Modified":"Sun, 16 Jul 2023 00:13:07 GMT","Permissions-Policy":"interest-cohort=()","Referrer-Policy":"no-referrer","Server":"nginx","Strict-Transport-Security":"max-age=63072000; includeSubdomains; preload","Transfer-Encoding":"chunked","Vary":"Cookie","Via":"1.1 a5f3f63e5cb1bdf37811b61ad2c25cbc.cloudfront.net (CloudFront)","X-Amz-Cf-Id":"YdUTkTMs9Gm_CUYloyk3Q5CnqDgAfuSIvsRsgTTJKg0oz0E55yl1kw==","X-Amz-Cf-Pop":"IAD55-P4","X-Cache":"Error from cloudfront","X-Content-Type-Options":"nosniff","X-Drupal-Cache":"MISS","X-Drupal-Dynamic-Cache":"HIT","X-Frame-Options":"SAMEORIGIN","X-XSS-Protection":"1; mode=block"},"ssl-verify":true,"status":"404"}