{"elapsed":"1.328","endpoint-url":"https://www.leeds.gov.uk/planning/community-infrastructure-levy/infrastructure-funding-statement","entry-date":"2022-06-14T00:09:39.772525","request-headers":{"Accept":"*/*","Accept-Encoding":"gzip, deflate","Connection":"keep-alive","User-Agent":"DLUHC Digital Land"},"response-headers":{"Cache-Control":"private","Content-Encoding":"gzip","Content-Type":"text/html; charset=utf-8","Date":"Tue, 14 Jun 2022 00:16:11 GMT","Expires":"Tue, 14 Jun 2022 00:19:12 GMT","SPIisLatency":"1","SPRequestDuration":"390","SPRequestGuid":"e31b47a0-6e85-70f0-20fc-a46b8937d7ac","Set-Cookie":"visid_incap_2048550=wQ/Xs/3HTQmXCnlTYa0YKUrTp2IAAAAAQUIPAAAAAADJ6TK21yGNcOzejy6Zjuko; expires=Tue, 13 Jun 2023 06:16:41 GMT; HttpOnly; path=/; Domain=.leeds.gov.uk, incap_ses_84_2048550=itsNZ2/1k1Y1fAvo2m0qAUvTp2IAAAAAH3u+4ngiSmq2VVxIenGNFw==; path=/; Domain=.leeds.gov.uk","Strict-Transport-Security":"max-age=15552000; includeSubDomains; preload","Transfer-Encoding":"chunked","Vary":"*","X-CDN":"Imperva","X-Content-Type-Options":"nosniff","X-FRAME-OPTIONS":"SAMEORIGIN","X-Iinfo":"11-10945760-10945762 NNNN CT(144 311 0) RT(1655165770766 12) q(0 0 5 0) r(10 10) U12","X-MS-InvokeApp":"1; RequireReadOnly","X-SharePointHealthScore":"0","request-id":"e31b47a0-6e85-70f0-20fc-a46b8937d7ac"},"ssl-verify":true,"status":"200"}