{"elapsed":"1.549","endpoint-url":"https://www.dudley.gov.uk/media/16877/dudley-infrastructure-funding-statement-2020-adopted.pdf","entry-date":"2024-01-17T00:07:42.524431","request-headers":{"Accept":"*/*","Accept-Encoding":"gzip, deflate","Connection":"keep-alive","User-Agent":"DLUHC Digital Land"},"resource":"c652fac55b6910644c8856da5b3f294d9358ae5753e14d878952dce53b9e0ef8","response-headers":{"Accept-Ranges":"bytes","Content-Length":"749683","Content-Type":"application/pdf","Date":"Wed, 17 Jan 2024 00:09:11 GMT","ETag":"\"1d6d52f1b2055f3\"","Last-Modified":"Fri, 18 Dec 2020 11:15:35 GMT","Set-Cookie":"TS015c65a0=0104e7c0621821a1277dee03724faf28b6e944b98be4e95e4699d3d510aaf8d3a9857ff5ac7cc8546c9fda60bb45792dd5eb4e7269; Path=/; Domain=.www.dudley.gov.uk; Secure; HTTPOnly"},"ssl-verify":true,"status":"200"}