{"bytes":935080,"elapsed":"0.583","endpoint-url":"https://crawley.gov.uk/sites/default/files/2020-12/Infrastructure_Funding_Statement_2019_2020.pdf","entry-date":"2022-03-13T00:05:33.643809","request-headers":{"Accept":"*/*","Accept-Encoding":"gzip, deflate","Connection":"keep-alive","User-Agent":"DLUHC Digital Land"},"resource":"3dded714e590eff05269597106d5f3091bd6d56e254037f304fe8b42fd423570","response-headers":{"Accept-Ranges":"bytes","Age":"0","Connection":"keep-alive","Content-Length":"935080","Content-Type":"application/pdf","Date":"Sun, 13 Mar 2022 00:05:47 GMT","Etag":"\"617dbbcb-e44a8\"","Last-Modified":"Sat, 30 Oct 2021 21:40:27 GMT","Server":"nginx","Strict-Transport-Security":"max-age=300","Traceparent":"00-df686c0754d346bab3fee0d4c78e2c3f-1d83ab359e5a8066-00","Via":"1.1 varnish, 1.1 varnish","X-Cache":"MISS, MISS","X-Cache-Hits":"0, 0","X-Cloud-Trace-Context":"df686c0754d346bab3fee0d4c78e2c3f/2126731695827353702;o=0","X-Pantheon-Styx-Hostname":"styx-fe1fe2-c-f8b5f496-7ff65","X-Served-By":"cache-ams12758-AMS, cache-iad-kiad7000081-IAD","X-Styx-Req-Id":"558c9464-a261-11ec-9c8e-1e6d2a6a3041","X-Timer":"S1647129947.191723,VS0,VE377"},"ssl-verify":true,"status":"200"}