{"elapsed":"0.628","endpoint-url":"https://www.derbyshiredales.gov.uk/images/S/DDDC_IFS_December_2020_Final_Version_21Dec2020.pdf","entry-date":"2024-02-07T00:06:47.040776","request-headers":{"Accept":"*/*","Accept-Encoding":"gzip, deflate","Connection":"keep-alive","User-Agent":"DLUHC Digital Land"},"response-headers":{"Cache-Control":"no-store, no-cache, must-revalidate, post-check=0, pre-check=0, no-cache, no-store, must-revalidate","Connection":"Keep-Alive","Content-Encoding":"gzip","Content-Type":"text/html; charset=utf-8","Date":"Wed, 07 Feb 2024 00:08:50 GMT","Expires":"Wed, 17 Aug 2005 00:00:00 GMT","Keep-Alive":"timeout=5, max=100","Last-Modified":"Wed, 07 Feb 2024 00:08:50 GMT","Pragma":"no-cache","Server":"Apache","Set-Cookie":"22247688f7395db38422b0545570b80f=6e51174fcc58d59486b6412fb0d69cfd; path=/; secure; HttpOnly","Strict-Transport-Security":"max-age=31536000","Transfer-Encoding":"chunked","Vary":"Accept-Encoding","X-Content-Type-Options":"nosniff","cross-origin-opener-policy":"same-origin","referrer-policy":"strict-origin-when-cross-origin","x-frame-options":"SAMEORIGIN"},"ssl-verify":true,"status":"404"}