{"bytes":1041680,"elapsed":"2.116","endpoint-url":"https://www.kirklees.gov.uk/beta/planning-policy/pdf/infrastructure-funding-statement-2020.pdf","entry-date":"2021-10-16T00:26:03.676852","request-headers":{"Accept":"*/*","Accept-Encoding":"gzip, deflate","Connection":"keep-alive","User-Agent":"Digital Land"},"resource":"7bc71c716645c65f33a1395980fff06e272ff9716cc84075023ff79dada6aa80","response-headers":{"Accept-Ranges":"bytes","Content-Length":"1041680","Content-Security-Policy":"frame-ancestors 'none';","Content-Type":"application/pdf","Date":"Sat, 16 Oct 2021 00:28:46 GMT","ETag":"\"24c1304261d4d61:0\"","Last-Modified":"Thu, 17 Dec 2020 10:42:04 GMT","Server":"Microsoft-IIS/10.0","Set-Cookie":"visid_incap_1963062=CgVOSzAWRhusQEHAY5blpb4camEAAAAAQUIPAAAAAABl1vwD1D88+CJf94+xPEM7; expires=Sat, 15 Oct 2022 05:48:02 GMT; HttpOnly; path=/; Domain=.kirklees.gov.uk, incap_ses_622_1963062=7+w5IGZ0HABpg6LCL8qhCL8camEAAAAAki2MoQHanm4FU08Kd3HRow==; path=/; Domain=.kirklees.gov.uk","Strict-Transport-Security":"max-age=31536000","X-CDN":"Imperva","X-Frame-Options":"SAMEORIGIN","X-Iinfo":"4-18556018-18556022 NNNN CT(82 171 0) RT(1634344126785 15) q(0 0 2 0) r(3 3) U12","X-Powered-By":"ASP.NET","X-UA-Compatible":"IE=edge"},"ssl-verify":true,"status":"200"}