{"elapsed":"0.995","endpoint-url":"https://www.knowsley.gov.uk/knowsleycouncil/media/Documents/S106-Infrastructure-Funding-Statement-2019-20.pdf","entry-date":"2023-11-07T00:05:50.135843","request-headers":{"Accept":"*/*","Accept-Encoding":"gzip, deflate","Connection":"keep-alive","User-Agent":"DLUHC Digital Land"},"response-headers":{"CF-Cache-Status":"MISS","CF-RAY":"82215e418f1b0ff0-LAX","Cache-Control":"max-age=14400","Connection":"keep-alive","Content-Encoding":"gzip","Content-Type":"text/html","Date":"Tue, 07 Nov 2023 00:13:04 GMT","Server":"cloudflare","Set-Cookie":"__cf_bm=4LVfC6MqGOJuA204MUE2MQiiecKauymlxA_RA1S22os-1699315984-0-AXTXe9BiGha/WBqzY/Nu3hN9gj4+A3j4cHJLNg+lkK1q71eCT+Ry+Xs4hNfvzI0RTU4ycWM/xSCjb9XFbMZ2V0A=; path=/; expires=Tue, 07-Nov-23 00:43:04 GMT; domain=.knowsley.gov.uk; HttpOnly; Secure; SameSite=None","Transfer-Encoding":"chunked","Vary":"Accept-Encoding","x-powered-by":"ASP.NET"},"ssl-verify":true,"status":"404"}