{"bytes":277815,"elapsed":"1.382","endpoint-url":"https://www.easthants.gov.uk/interim-infrastructure-funding-statement-december-2020-pdf-271-kb","entry-date":"2022-03-31T00:07:13.074832","request-headers":{"Accept":"*/*","Accept-Encoding":"gzip, deflate","Connection":"keep-alive","User-Agent":"DLUHC Digital Land"},"resource":"8b656ab244bc6a4570705b0a29e260921a55a6b992c924b32dfbff39ae2b1f19","response-headers":{"Accept-Ranges":"bytes","Connection":"keep-alive","Content-Length":"277815","Content-Type":"application/pdf","Date":"Thu, 31 Mar 2022 00:10:57 GMT","ETag":"\"1fa822f29179200af108eead7cd854c0\"","Last-Modified":"Fri, 18 Dec 2020 16:36:09 GMT","Server":"AmazonS3","Via":"1.1 adb1632aa800f446f3f4e7b45c9dfd3e.cloudfront.net (CloudFront)","X-Amz-Cf-Id":"sce3BltNVzabvoKLhAQFtHAG-WVBeCoqiD8OkEFy42uxzAKc0fXfqA==","X-Amz-Cf-Pop":"IAD89-P2","X-Cache":"Miss from cloudfront"},"ssl-verify":true,"status":"200"}