{"elapsed":"0.448","endpoint-url":"https://cdn.havant.gov.uk/public/documents/AMR%202018%20(CIL).pdf","entry-date":"2021-11-06T00:24:26.429091","request-headers":{"Accept":"*/*","Accept-Encoding":"gzip, deflate","Connection":"keep-alive","User-Agent":"Digital Land"},"resource":"0b2e3a24d7afaf246af59140acf3a6b6dd251bf7492e7ac6a97a6752da51c0af","response-headers":{"Accept-Ranges":"bytes","Connection":"keep-alive","Content-Length":"20264","Content-Type":"application/pdf","Date":"Sat, 06 Nov 2021 00:24:38 GMT","ETag":"\"1eaac4ee019000031abfb8aec76e1ebe\"","Last-Modified":"Mon, 14 Dec 2020 08:41:34 GMT","Server":"AmazonS3","Via":"1.1 077b94dab77b8114aebf503be197d7d9.cloudfront.net (CloudFront)","X-Amz-Cf-Id":"fDx28dtj0boP2EgZyyuAU4rRKMMx8nDmPv0-_rWc_qm9RXtVvT9knw==","X-Amz-Cf-Pop":"IAD89-C3","X-Cache":"Miss from cloudfront"},"ssl-verify":true,"status":"200"}