{"elapsed":"1.039","endpoint-url":"https://www.easthants.gov.uk/interim-infrastructure-funding-statement-year-ending-31-march-2020-pdf-271-kb","entry-date":"2022-06-08T00:06:39.542862","request-headers":{"Accept":"*/*","Accept-Encoding":"gzip, deflate","Connection":"keep-alive","User-Agent":"DLUHC Digital Land"},"resource":"8b656ab244bc6a4570705b0a29e260921a55a6b992c924b32dfbff39ae2b1f19","response-headers":{"Accept-Ranges":"bytes","Connection":"keep-alive","Content-Length":"277815","Content-Type":"application/pdf","Date":"Wed, 08 Jun 2022 00:13:37 GMT","ETag":"\"1fa822f29179200af108eead7cd854c0\"","Last-Modified":"Wed, 22 Dec 2021 15:05:18 GMT","Server":"AmazonS3","Via":"1.1 155773739ab9d0052969b92a43e543d8.cloudfront.net (CloudFront)","X-Amz-Cf-Id":"jEwB1HdBHacE_xP2kNCXEo4GnRE6BptIUBbLk8ouT6jmvt1y-jFUhw==","X-Amz-Cf-Pop":"ORD53-C3","X-Cache":"Miss from cloudfront"},"ssl-verify":true,"status":"200"}