{"elapsed":"1.222","endpoint-url":"http://www.fareham.gov.uk/PDF/planning/local_plan/FarehamBoroughCouncilInfrastructureFundingStatement19-20.pdf","entry-date":"2022-01-02T00:29:31.813034","request-headers":{"Accept":"*/*","Accept-Encoding":"gzip, deflate","Connection":"keep-alive","User-Agent":"DLUHC Digital Land"},"resource":"0260ceb2ea6463461721c7e28b1a4dd9541d51aecb12eb9cf99199d14c3cd301","response-headers":{"Accept-Ranges":"bytes","Content-Length":"225882","Content-Type":"application/pdf","Date":"Sun, 02 Jan 2022 00:29:32 GMT","ETag":"\"7aa9faee1d9d61:0\"","Last-Modified":"Wed, 23 Dec 2020 08:02:18 GMT","Server":"Microsoft-IIS/7.5","Set-Cookie":"ApplicationGatewayAffinity=89b0f6b4e7076d0b5f212af4dacca7c9c6d38cf88bc60ba1d9330360f9deddcf;Path=/;Domain=www.fareham.gov.uk, ApplicationGatewayAffinityCORS=89b0f6b4e7076d0b5f212af4dacca7c9c6d38cf88bc60ba1d9330360f9deddcf;Path=/;Domain=www.fareham.gov.uk;SameSite=None;Secure","X-Powered-By":"ASP.NET"},"ssl-verify":true,"status":"200"}