{"elapsed":"1.618","endpoint-url":"https://www.leeds.gov.uk/planning/community-infrastructure-levy/infrastructure-funding-statement","entry-date":"2022-12-13T15:05:07.816978","request-headers":{"Accept":"*/*","Accept-Encoding":"gzip, deflate","Connection":"keep-alive","User-Agent":"DLUHC Digital Land"},"response-headers":{"Cache-Control":"private","Content-Encoding":"gzip","Content-Type":"text/html; charset=utf-8","Date":"Tue, 13 Dec 2022 15:12:28 GMT","Expires":"Tue, 13 Dec 2022 15:15:29 GMT","SPIisLatency":"1","SPRequestDuration":"265","SPRequestGuid":"83e381a0-6e4a-70f0-9e18-36ba70e9a37f","Set-Cookie":"visid_incap_2048550=5LjXT/e/QxOCMZwk3rejDVyWmGMAAAAAQUIPAAAAAABl57Z8SleXtE2IFYU8BDfE; expires=Wed, 13 Dec 2023 06:19:26 GMT; HttpOnly; path=/; Domain=.leeds.gov.uk, incap_ses_208_2048550=cjj5DynfG2VdKlAUpffiAl2WmGMAAAAALdRHDNRF7AOaNbGA220FIw==; path=/; Domain=.leeds.gov.uk","Strict-Transport-Security":"max-age=15552000; includeSubDomains; preload","Transfer-Encoding":"chunked","Vary":"*","X-CDN":"Imperva","X-Content-Type-Options":"nosniff","X-FRAME-OPTIONS":"SAMEORIGIN","X-Iinfo":"6-185257385-185257408 NNNN CT(134 674 0) RT(1670944348107 110) q(0 0 8 3) r(12 12) U12","X-MS-InvokeApp":"1; RequireReadOnly","X-SharePointHealthScore":"0","request-id":"83e381a0-6e4a-70f0-9e18-36ba70e9a37f"},"ssl-verify":true,"status":"200"}