{"bytes":991728,"elapsed":"2.221","endpoint-url":"https://lewisham.gov.uk/-/media/files/imported/ifs2019_2020.ashx","entry-date":"2021-12-01T00:28:13.231375","request-headers":{"Accept":"*/*","Accept-Encoding":"gzip, deflate","Connection":"keep-alive","User-Agent":"Digital Land"},"resource":"48e812927803dc4778b2ee5d468f36f8d0d1e000f5be0280eb8e20941d9efe12","response-headers":{"Accept-Ranges":"bytes","Cache-Control":"private, max-age=604800","Content-Disposition":"attachment; filename=\"IFS2019_2020.pdf\"","Content-Length":"991728","Content-Type":"application/pdf","Date":"Wed, 01 Dec 2021 00:28:36 GMT","Expires":"Wed, 08 Dec 2021 00:28:36 GMT","Last-Modified":"Mon, 07 Jun 2021 13:36:14 GMT","Server":"Microsoft-IIS/10.0","Set-Cookie":"ASP.NET_SessionId=kdwndi3acomcfhk2z3j0mj1s; path=/; HttpOnly, SC_ANALYTICS_GLOBAL_COOKIE=5f5f6e01d31b45a9913d98777266d388|False; expires=Sat, 29-Nov-2031 00:28:36 GMT; path=/; HttpOnly","Strict-Transport-Security":"max-age=31536000","X-Content-Type-Options":"nosniff","X-Test":"1","X-XSS-Protection":"1; mode=block"},"ssl-verify":true,"status":"200"}