{"elapsed":"0.69","endpoint-url":"https://cdn.havant.gov.uk/public/documents/2016%20CIL%20Monitoring.pdf","entry-date":"2022-08-20T00:05:47.635818","request-headers":{"Accept":"*/*","Accept-Encoding":"gzip, deflate","Connection":"keep-alive","User-Agent":"DLUHC Digital Land"},"resource":"d5a142be10893776bf97eebf12be7b7b98037721023ce09b7f4121a4f89a1e65","response-headers":{"Accept-Ranges":"bytes","Connection":"keep-alive","Content-Length":"10213","Content-Type":"application/pdf","Date":"Sat, 20 Aug 2022 00:06:03 GMT","ETag":"\"1a6aadfb2561af0a71f3427b67fc99e4\"","Last-Modified":"Mon, 14 Dec 2020 08:41:34 GMT","Server":"AmazonS3","Via":"1.1 28e742836f2fd5cfaf44dddd4dcdf6b8.cloudfront.net (CloudFront)","X-Amz-Cf-Id":"tNj1im2LEB7NkaVLArDPU_bcZQ0D4OcKKZKl85pCmx85Lhf5VSVVgA==","X-Amz-Cf-Pop":"LAX3-C3","X-Cache":"Miss from cloudfront"},"ssl-verify":true,"status":"200"}