{"elapsed":"3.578","endpoint-url":"https://www.dudley.gov.uk/media/16877/dudley-infrastructure-funding-statement-2020-adopted.pdf","entry-date":"2023-09-25T00:07:28.498277","request-headers":{"Accept":"*/*","Accept-Encoding":"gzip, deflate","Connection":"keep-alive","User-Agent":"DLUHC Digital Land"},"resource":"c652fac55b6910644c8856da5b3f294d9358ae5753e14d878952dce53b9e0ef8","response-headers":{"Accept-Ranges":"bytes","Content-Length":"749683","Content-Type":"application/pdf","Date":"Mon, 25 Sep 2023 00:10:53 GMT","ETag":"\"aa53831b2fd5d61:0\"","Last-Modified":"Fri, 18 Dec 2020 11:15:35 GMT","Set-Cookie":"TS015c65a0=0104e7c06247d83bef6657e8c5953ae20ca9e2892514778507f5e29abd9a1f366e5dd3463c6f2c2b312c9d9b43dc6d82f79efb85db; Path=/; Domain=.www.dudley.gov.uk; Secure; HTTPOnly"},"ssl-verify":true,"status":"200"}