{"elapsed":"0.379","endpoint-url":"https://www.eastcambs.gov.uk/sites/default/files/Infrastructure%20Funding%20Statement%202019-2020.pdf","entry-date":"2022-05-16T00:08:16.381080","request-headers":{"Accept":"*/*","Accept-Encoding":"gzip, deflate","Connection":"keep-alive","User-Agent":"DLUHC Digital Land"},"resource":"ef25dc1f8f253195c110e2e8e23f9d1d4124ba792407a13182bae4d8d17f90bd","response-headers":{"Accept-Ranges":"bytes","Age":"0","Connection":"keep-alive","Content-Length":"210004","Content-Type":"application/pdf","Date":"Mon, 16 May 2022 00:10:05 GMT","Etag":"\"626ad58a-33454\"","Last-Modified":"Thu, 28 Apr 2022 17:57:30 GMT","Server":"nginx","Strict-Transport-Security":"max-age=300","Traceparent":"00-01f895fc10684256abfe2fa4763c96c3-4f34191d621edbe1-00","Via":"1.1 varnish, 1.1 varnish","X-Cache":"MISS, MISS","X-Cache-Hits":"0, 0","X-Cloud-Trace-Context":"01f895fc10684256abfe2fa4763c96c3/5707214241776196577;o=0","X-Pantheon-Styx-Hostname":"styx-fe3fe4-c-84b77b49bd-wh8c8","X-Served-By":"cache-ams12728-AMS, cache-iad-kiad7000066-IAD","X-Styx-Req-Id":"8a21667b-d4ac-11ec-b378-d29d359436d2","X-Timer":"S1652659806.804035,VS0,VE175"},"ssl-verify":true,"status":"200"}