{"elapsed":"0.651","endpoint-url":"https://www.knowsley.gov.uk/knowsleycouncil/media/Documents/S106-Infrastructure-Funding-Statement-2019-20.pdf","entry-date":"2023-11-27T00:08:39.817414","request-headers":{"Accept":"*/*","Accept-Encoding":"gzip, deflate","Connection":"keep-alive","User-Agent":"DLUHC Digital Land"},"response-headers":{"CF-Cache-Status":"MISS","CF-RAY":"82c629ffde8a2d0a-IAD","Cache-Control":"max-age=14400","Connection":"keep-alive","Content-Encoding":"gzip","Content-Type":"text/html","Date":"Mon, 27 Nov 2023 00:13:13 GMT","Server":"cloudflare","Set-Cookie":"__cf_bm=4sMytA6S.FDW_zSl4Hu41jxG.a88ohwc1UirE_v5tZ8-1701043993-0-AdvUUEs9AhyPrg348AAoiQl9/DPMi/+ZfqrrjaWmJH8KXDfrSAUjW0/jkT/KZQzdtBukOR5tCYZfFnyRMaa7vvI=; path=/; expires=Mon, 27-Nov-23 00:43:13 GMT; domain=.knowsley.gov.uk; HttpOnly; Secure; SameSite=None","Transfer-Encoding":"chunked","Vary":"Accept-Encoding","x-powered-by":"ASP.NET"},"ssl-verify":true,"status":"404"}