{"elapsed":"2.532","endpoint-url":"https://www.carlisle.gov.uk/Portals/24/Documents/Evidence_Base/IFS/Carlisle%20IFS%202019.20.pdf","entry-date":"2023-05-09T00:06:36.438069","request-headers":{"Accept":"*/*","Accept-Encoding":"gzip, deflate","Connection":"keep-alive","User-Agent":"DLUHC Digital Land"},"resource":"2e2c2240217726a402e97be53c3ae0f19c82c005228cbfa76ec0ed2e04bf24b6","response-headers":{"Accept-Ranges":"bytes","CF-Cache-Status":"MISS","CF-RAY":"7c45b41ecaa038fe-IAD","Cache-Control":"max-age=691200","Connection":"keep-alive","Content-Length":"65834","Content-Type":"application/pdf","Date":"Tue, 09 May 2023 00:07:42 GMT","NEL":"{\"success_fraction\":0,\"report_to\":\"cf-nel\",\"max_age\":604800}","Report-To":"{\"endpoints\":[{\"url\":\"https:\\/\\/a.nel.cloudflare.com\\/report\\/v3?s=5tCItdTJ8mCKRCG6iPqzENjAGmfU7YgwdQtyG9jdpp95in7I%2BBG%2BBIVGMJ0wmbXVAX9VTyhjNRifxkPaDpEo%2FB6v9b77jA9viAYFA3MKT67I99TQO%2BHcvSBXs2NOyg2BsY0xba4%3D\"}],\"group\":\"cf-nel\",\"max_age\":604800}","Server":"cloudflare","Vary":"Accept-Encoding","etag":"\"c25ae4da30e8d61:0\"","last-modified":"Mon, 11 Jan 2021 15:45:58 GMT","strict-transport-security":"max-age=63072000","x-content-type-options":"nosniff","x-frame-options":"SAMEORIGIN","x-ua-compatible":"IE=edge","x-xss-protection":"1; mode=block"},"ssl-verify":true,"status":"200"}