{"bytes":191770,"elapsed":"1.371","endpoint-url":"https://www.daventrydc.gov.uk/EasySiteWeb/GatewayLink.aspx?alId=51900","entry-date":"2021-10-29T00:23:32.899841","request-headers":{"Accept":"*/*","Accept-Encoding":"gzip, deflate","Connection":"keep-alive","Cookie":"ASP.NET_SessionId=5hl4dqgtekbq51boazucdytm; HASH_ASP.NET_SessionId=C70B11A5E2A090EF8147F0DC183D74594E15A776","User-Agent":"Digital Land"},"resource":"bd94fe78bcbf2439f4bb0e9e879a410c94f3736933377ed009322ba459075c15","response-headers":{"Cache-Control":"public,Private","Connection":"Keep-Alive","Content-Disposition":"attachment; filename=\"Annual Infrastructure Funding Statement 2019-20 Accessible.pdf\"","Content-Encoding":"gzip","Content-Type":"application/pdf","Date":"Fri, 29 Oct 2021 00:28:12 GMT","ETag":"\"730B65DA1989BB1B384910934705B94F-gzip\"","Expires":"Fri, 29 Oct 2021 00:28:13 GMT","Keep-Alive":"timeout=15, max=99","Last-Modified":"Fri, 18 Dec 2020 15:33:18 GMT","Server":"Apache","Transfer-Encoding":"chunked","Vary":"Accept-Encoding","X-Powered-By":"ASP.NET","X-UA-Compatible":"IE=edge"},"ssl-verify":true,"status":"200"}