{"elapsed":"0.697","endpoint-url":"https://www.hart.gov.uk/sites/default/files/4_The_Council/Policies_and_published_documents/Planning_policy/Final%20version%202%20corrected%20IFS%2020-21_1.pdf","entry-date":"2023-10-15T00:07:22.847995","request-headers":{"Accept":"*/*","Accept-Encoding":"gzip, deflate","Connection":"keep-alive","User-Agent":"DLUHC Digital Land"},"response-headers":{"Cache-Control":"max-age=1800, public","Connection":"keep-alive","Content-Language":"en","Content-Type":"text/html; charset=UTF-8","Date":"Sun, 15 Oct 2023 00:19:31 GMT","ETag":"\"1697327840\"","Expires":"Sun, 19 Nov 1978 05:00:00 GMT","Last-Modified":"Sat, 14 Oct 2023 23:57:20 GMT","Permissions-Policy":"interest-cohort=()","Referrer-Policy":"no-referrer","Server":"nginx","Strict-Transport-Security":"max-age=63072000; includeSubdomains; preload","Transfer-Encoding":"chunked","Vary":"Cookie","Via":"1.1 8c17de0f985b9ec9dbef8f79e2137106.cloudfront.net (CloudFront)","X-Amz-Cf-Id":"mPfdwkN48JwODAh2BUI7YbX1AjhGw94D78ydzdJbEY-q7UQ8umIBcQ==","X-Amz-Cf-Pop":"JFK50-P3","X-Cache":"Error from cloudfront","X-Content-Type-Options":"nosniff","X-Drupal-Cache":"HIT","X-Drupal-Dynamic-Cache":"HIT","X-Frame-Options":"SAMEORIGIN","X-XSS-Protection":"1; mode=block"},"ssl-verify":true,"status":"404"}