{"elapsed":"0.888","endpoint-url":"https://cdn.havant.gov.uk/public/documents/2019%20CIL%20Monitoring.pdf","entry-date":"2023-11-11T00:05:50.680168","request-headers":{"Accept":"*/*","Accept-Encoding":"gzip, deflate","Connection":"keep-alive","User-Agent":"DLUHC Digital Land"},"resource":"3b1eb7aeae299dfaae06b3b718890e7f068f1f50d9c419720bb0824236ae86de","response-headers":{"Accept-Ranges":"bytes","Connection":"keep-alive","Content-Length":"807084","Content-Type":"application/pdf","Date":"Sat, 11 Nov 2023 00:06:04 GMT","ETag":"\"c3faf38e2e1b3a3dc6101f397ae00a05\"","Last-Modified":"Mon, 14 Dec 2020 08:41:34 GMT","Server":"AmazonS3","Via":"1.1 7c2bddae46164995fddee85f5e85fca2.cloudfront.net (CloudFront)","X-Amz-Cf-Id":"OMfll577JwQUQKKVqetphH9Sc0wo0q87ZQIH6l94nCCjh6ZptEUiLA==","X-Amz-Cf-Pop":"ORD56-P4","X-Cache":"Miss from cloudfront"},"ssl-verify":true,"status":"200"}