{"elapsed":"2.457","endpoint-url":"https://www.gloucestershire.gov.uk/media/2103790/gcc-draft-infrastructure-funding-statement-2019_20-final.pdf","entry-date":"2023-02-23T00:06:13.010194","request-headers":{"Accept":"*/*","Accept-Encoding":"gzip, deflate","Connection":"keep-alive","User-Agent":"DLUHC Digital Land"},"response-headers":{"Cache-Control":"private","Content-Length":"28852","Content-Type":"text/html; charset=utf-8","Date":"Thu, 23 Feb 2023 00:10:29 GMT","Set-Cookie":"ASP.NET_SessionId=exe4tesy5psii5vdn2d2mrsv; path=/; HttpOnly; SameSite=Lax, ASP.NET_SessionId=exe4tesy5psii5vdn2d2mrsv; path=/; HttpOnly; SameSite=Lax, pcg_HP=1510; expires=Sat, 25-Mar-2023 00:10:29 GMT; path=/"},"ssl-verify":true,"status":"404"}