{"bytes":65834,"elapsed":"1.144","endpoint-url":"https://www.carlisle.gov.uk/Portals/24/Documents/Evidence_Base/IFS/Carlisle%20IFS%202019.20.pdf","entry-date":"2022-03-29T00:10:22.947593","request-headers":{"Accept":"*/*","Accept-Encoding":"gzip, deflate","Connection":"keep-alive","User-Agent":"DLUHC Digital Land"},"resource":"2e2c2240217726a402e97be53c3ae0f19c82c005228cbfa76ec0ed2e04bf24b6","response-headers":{"Accept-Ranges":"bytes","CF-Cache-Status":"MISS","CF-RAY":"6f3467b47d4996c5-SJC","Cache-Control":"max-age=691200","Connection":"keep-alive","Content-Length":"65834","Content-Type":"application/pdf","Date":"Tue, 29 Mar 2022 00:14:24 GMT","Expect-CT":"max-age=604800, report-uri=\"https://report-uri.cloudflare.com/cdn-cgi/beacon/expect-ct\"","NEL":"{\"success_fraction\":0,\"report_to\":\"cf-nel\",\"max_age\":604800}","Report-To":"{\"endpoints\":[{\"url\":\"https:\\/\\/a.nel.cloudflare.com\\/report\\/v3?s=14w0m6iywkoQ9vfaEZoRd1Kfo0K8f%2FS8HCk0S0BsJKQkeY04QEkbU29YQoeSg9h64OrzyG79seo6cJPKgAclFdGRwJ75zGSWSccnieduYJnxKsDy46tVWF0glTvIL%2F72hPgzC%2BM%3D\"}],\"group\":\"cf-nel\",\"max_age\":604800}","Server":"cloudflare","Vary":"Accept-Encoding","etag":"\"c25ae4da30e8d61:0\"","last-modified":"Mon, 11 Jan 2021 15:45:58 GMT","strict-transport-security":"max-age=63072000","x-content-type-options":"nosniff","x-frame-options":"SAMEORIGIN","x-ua-compatible":"IE=edge","x-xss-protection":"1; mode=block"},"ssl-verify":true,"status":"200"}