{"elapsed":"6.61","endpoint-url":"https://www.hambleton.gov.uk/downloads/file/2136/infrastructure-funding-statement-2020","entry-date":"2023-09-27T00:07:32.390153","request-headers":{"Accept":"*/*","Accept-Encoding":"gzip, deflate","Connection":"keep-alive","User-Agent":"DLUHC Digital Land"},"response-headers":{"Cache-Control":"max-age=900, public","Connection":"keep-alive","Content-Encoding":"gzip","Content-Language":"en","Content-Type":"text/html; charset=UTF-8","Date":"Tue, 26 Sep 2023 23:50:25 GMT","ETag":"W/\"1695772225\"","Expires":"Sun, 19 Nov 1978 05:00:00 GMT","Last-Modified":"Tue, 26 Sep 2023 23:50:25 GMT","Server":"nginx","Transfer-Encoding":"chunked","Vary":"Accept-Encoding,Cookie","Via":"1.1 d591fee4e3f29cf0e3380368d25b4a40.cloudfront.net (CloudFront)","X-Amz-Cf-Id":"egmoq7_ydTPZ9AiTPEu5q7IQ4z8WSiwzOQj-dfF_NL6uBMwt5yOvQA==","X-Amz-Cf-Pop":"IAD89-P1","X-Cache":"Miss from cloudfront","X-Content-Type-Options":"nosniff, nosniff","X-Drupal-Cache":"HIT","X-Drupal-Dynamic-Cache":"MISS","X-Frame-Options":"SAMEORIGIN","X-Generator":"Drupal 9 (https://www.drupal.org)","X-UA-Compatible":"IE=edge"},"ssl-verify":true,"status":"200"}