{"elapsed":"1.609","endpoint-url":"https://www.bradford.gov.uk/media/6150/infrastructure-funding-statement-2019-20.pdf","entry-date":"2022-07-25T00:07:06.398292","request-headers":{"Accept":"*/*","Accept-Encoding":"gzip, deflate","Connection":"keep-alive","User-Agent":"DLUHC Digital Land"},"resource":"d388c12ad9cc3e076f3d12b5c431dde02560992808f8e05d3238b22c26730f4b","response-headers":{"Accept-Ranges":"bytes","Content-Length":"2670190","Content-Type":"application/pdf","Date":"Mon, 25 Jul 2022 00:07:42 GMT","ETag":"\"NS-1fedb73a6630-90b569fe83d4d61:0\"","Last-Modified":"Thu, 17 Dec 2020 14:50:42 GMT","Set-Cookie":"visid_incap_1845735=ZLtQV8dYRd+5jw1uGdGc2QDf3WIAAAAAQUIPAAAAAABMsv+8jAA5GWytiqj2fHpH; expires=Mon, 24 Jul 2023 08:17:04 GMT; HttpOnly; path=/; Domain=.bradford.gov.uk, incap_ses_1358_1845735=pO8/fOnyvxSZRN/US5bYEgDf3WIAAAAAoXX/VGV+DzJGkFXI5W4IBw==; path=/; Domain=.bradford.gov.uk","X-CDN":"Imperva","X-Frame-Options":"sameorigin","X-Iinfo":"14-104360333-104251679 pNNN RT(1658707712413 34) q(0 0 0 0) r(7 7) U12"},"ssl-verify":true,"status":"200"}