{"elapsed":"1.197","endpoint-url":"https://www.leeds.gov.uk/planning/community-infrastructure-levy/infrastructure-funding-statement","entry-date":"2023-03-25T00:06:24.375870","request-headers":{"Accept":"*/*","Accept-Encoding":"gzip, deflate","Connection":"keep-alive","User-Agent":"DLUHC Digital Land"},"response-headers":{"Cache-Control":"private","Content-Encoding":"gzip","Content-Type":"text/html; charset=utf-8","Date":"Sat, 25 Mar 2023 00:15:51 GMT","Expires":"Sat, 25 Mar 2023 00:18:52 GMT","SPIisLatency":"1","SPRequestDuration":"253","SPRequestGuid":"bf84a2a0-bebc-70f0-20fc-afd23bb2773c","Set-Cookie":"visid_incap_2048550=QGmR6AU6QQiZoHqn6qtwgjY9HmQAAAAAQUIPAAAAAACQ8piPbLmojqLCHzZxgWDZ; expires=Sat, 23 Mar 2024 08:40:50 GMT; HttpOnly; path=/; Domain=.leeds.gov.uk, incap_ses_1439_2048550=oKgORHipnlhbnJPJsVv4Ezc9HmQAAAAAYVNo6n15t38hEz1IQL8ssA==; path=/; Domain=.leeds.gov.uk","Strict-Transport-Security":"max-age=15552000; includeSubDomains; preload","Transfer-Encoding":"chunked","Vary":"*","X-CDN":"Imperva","X-Content-Type-Options":"nosniff","X-FRAME-OPTIONS":"SAMEORIGIN","X-Iinfo":"2-7783141-7783143 NNNN CT(132 288 0) RT(1679703350873 85) q(0 0 4 0) r(8 8) U12","X-MS-InvokeApp":"1; RequireReadOnly","X-SharePointHealthScore":"0","request-id":"bf84a2a0-bebc-70f0-20fc-afd23bb2773c"},"ssl-verify":true,"status":"200"}