{"elapsed":"5.238","endpoint-url":"https://www.dudley.gov.uk/media/16877/dudley-infrastructure-funding-statement-2020-adopted.pdf","entry-date":"2023-11-22T00:07:08.380308","request-headers":{"Accept":"*/*","Accept-Encoding":"gzip, deflate","Connection":"keep-alive","User-Agent":"DLUHC Digital Land"},"resource":"c652fac55b6910644c8856da5b3f294d9358ae5753e14d878952dce53b9e0ef8","response-headers":{"Accept-Ranges":"bytes","Content-Length":"749683","Content-Type":"application/pdf","Date":"Wed, 22 Nov 2023 00:09:21 GMT","ETag":"\"1d6d52f1b2055f3\"","Last-Modified":"Fri, 18 Dec 2020 11:15:35 GMT","Set-Cookie":"TS015c65a0=0104e7c062a2895d893f48799c1db5c3e39c7115f920958a9d1f650843a34d253a59ab81934f00dca00c3d2be6056f5810df6b38e5; Path=/; Domain=.www.dudley.gov.uk; Secure; HTTPOnly"},"ssl-verify":true,"status":"200"}