{"elapsed":"1.373","endpoint-url":"https://www.bradford.gov.uk/media/6150/infrastructure-funding-statement-2019-20.pdf","entry-date":"2021-12-07T00:27:40.612576","request-headers":{"Accept":"*/*","Accept-Encoding":"gzip, deflate","Connection":"keep-alive","User-Agent":"Digital Land"},"resource":"d388c12ad9cc3e076f3d12b5c431dde02560992808f8e05d3238b22c26730f4b","response-headers":{"Accept-Ranges":"bytes","Content-Length":"2670190","Content-Type":"application/pdf","Date":"Tue, 07 Dec 2021 00:29:21 GMT","ETag":"\"NS-1fedb73a6630-90b569fe83d4d61:0\"","Last-Modified":"Thu, 17 Dec 2020 14:50:42 GMT","Set-Cookie":"visid_incap_1845735=GWkNOU/jT72tBXMXzbgqO+6qrmEAAAAAQUIPAAAAAAD9u+2GSRuu195rl5eyMuDJ; expires=Tue, 06 Dec 2022 11:29:15 GMT; HttpOnly; path=/; Domain=.bradford.gov.uk, incap_ses_725_1845735=YjANGviDJE5qPJX1KLgPCu6qrmEAAAAAJdFURl33LaGy/UKQzWqC4Q==; path=/; Domain=.bradford.gov.uk","X-CDN":"Imperva","X-Frame-Options":"sameorigin","X-Iinfo":"10-184438800-184438464 pNNN RT(1638836974474 37) q(0 0 0 1) r(1 1) U12"},"ssl-verify":true,"status":"200"}