{"elapsed":"0.689","endpoint-url":"https://www.havant.gov.uk/s106-annual-monitoring-report-2016-pdf-109-kb","entry-date":"2021-12-21T00:29:50.110007","request-headers":{"Accept":"*/*","Accept-Encoding":"gzip, deflate","Connection":"keep-alive","User-Agent":"DLUHC Digital Land"},"resource":"c6deab0caad0706b2bf77e3c29914e7622bd4790cd9734d8cc8b165cfd59566a","response-headers":{"Accept-Ranges":"bytes","Connection":"keep-alive","Content-Length":"111788","Content-Type":"application/pdf","Date":"Tue, 21 Dec 2021 00:32:03 GMT","ETag":"\"fde940916d256e5d7821ef2fb9f705ae\"","Last-Modified":"Mon, 14 Dec 2020 08:41:34 GMT","Server":"AmazonS3","Via":"1.1 d01a0cfc47d6e412dd81c986ff5d69db.cloudfront.net (CloudFront)","X-Amz-Cf-Id":"BNiYhs1CdvW-HRaZgTq7K2A_9i20foAqvVr-0mxaO-BiHYLh2lMa7w==","X-Amz-Cf-Pop":"IAD50-C2","X-Cache":"RefreshHit from cloudfront"},"ssl-verify":true,"status":"200"}