{"elapsed":"1.343","endpoint-url":"https://www.leeds.gov.uk/planning/community-infrastructure-levy/infrastructure-funding-statement","entry-date":"2023-07-11T00:07:16.814287","request-headers":{"Accept":"*/*","Accept-Encoding":"gzip, deflate","Connection":"keep-alive","User-Agent":"DLUHC Digital Land"},"response-headers":{"Cache-Control":"private","Content-Encoding":"gzip","Content-Type":"text/html; charset=utf-8","Date":"Tue, 11 Jul 2023 00:12:32 GMT","Expires":"Tue, 11 Jul 2023 00:15:32 GMT","SPIisLatency":"1","SPRequestDuration":"337","SPRequestGuid":"7b47c5a0-4ef6-70f0-9e18-397c436ff85f","Set-Cookie":"visid_incap_2048550=xCsWtN5CS9iaDRwIpluVt2+erGQAAAAAQUIPAAAAAABgHeBNN2G5jTPK4exLR6If; expires=Tue, 09 Jul 2024 07:14:44 GMT; HttpOnly; path=/; Domain=.leeds.gov.uk, incap_ses_201_2048550=M683SVNuxF7qLAG1lBjKAm+erGQAAAAAtIDegb3wWPK4QCDn0MRS3A==; path=/; Domain=.leeds.gov.uk","Strict-Transport-Security":"max-age=15552000; includeSubDomains; preload","Transfer-Encoding":"chunked","Vary":"*","X-CDN":"Imperva","X-Content-Type-Options":"nosniff","X-FRAME-OPTIONS":"SAMEORIGIN","X-Iinfo":"13-104076556-104076561 NNNN CT(131 310 0) RT(1689034350952 110) q(0 0 5 0) r(9 9) U12","X-MS-InvokeApp":"1; RequireReadOnly","X-SharePointHealthScore":"0","request-id":"7b47c5a0-4ef6-70f0-9e18-397c436ff85f"},"ssl-verify":true,"status":"200"}