{"elapsed":"0.615","endpoint-url":"https://cdn.havant.gov.uk/public/documents/2016%20CIL%20Monitoring.pdf","entry-date":"2023-10-07T00:05:47.594562","request-headers":{"Accept":"*/*","Accept-Encoding":"gzip, deflate","Connection":"keep-alive","User-Agent":"DLUHC Digital Land"},"resource":"d5a142be10893776bf97eebf12be7b7b98037721023ce09b7f4121a4f89a1e65","response-headers":{"Accept-Ranges":"bytes","Connection":"keep-alive","Content-Length":"10213","Content-Type":"application/pdf","Date":"Sat, 07 Oct 2023 00:06:03 GMT","ETag":"\"1a6aadfb2561af0a71f3427b67fc99e4\"","Last-Modified":"Mon, 14 Dec 2020 08:41:34 GMT","Server":"AmazonS3","Via":"1.1 b120e3774f3cfb82b3f2af8dd84a9e72.cloudfront.net (CloudFront)","X-Amz-Cf-Id":"fs329E8RYCRSQP1cKGX1BmT4zYwtZUhJ6rJIh-8yVncvLlmwE4ZsBA==","X-Amz-Cf-Pop":"LAX53-P4","X-Cache":"RefreshHit from cloudfront"},"ssl-verify":true,"status":"200"}