{"elapsed":"0.165","endpoint-url":"https://assets.ctfassets.net/knkzaf64jx5x/1Cs2QGhxfhitEJ14P9Ibi7/601a009d82acecc769b28a5a8d2e088c/Essex_County_Council_Infrastructure_Funding_Statement_19_20.pdf","entry-date":"2023-08-16T00:06:19.131084","request-headers":{"Accept":"*/*","Accept-Encoding":"gzip, deflate","Connection":"keep-alive","User-Agent":"DLUHC Digital Land"},"response-headers":{"Cache-Control":"max-age=300","Connection":"keep-alive","Content-Length":"109","Content-Type":"application/json","Date":"Wed, 16 Aug 2023 00:06:22 GMT","Server":"CloudFront","Via":"1.1 3b2c32f90b8e4193dda6d9be63628ab2.cloudfront.net (CloudFront)","X-Amz-Cf-Id":"Sz2vyvQL3UfYvvrFjq8kaj3fNmDSBuboXu3q4Lp17TdHT9wF_XFidw==","X-Amz-Cf-Pop":"IAD55-P3","X-Cache":"Miss from cloudfront"},"ssl-verify":true,"status":"404"}