{"elapsed":"0.277","endpoint-url":"https://raw.githubusercontent.com/digital-land/infrastructure-funding-statement-collection/main/data/infrastructure-funding-statement.csv","entry-date":"2023-06-26T00:08:02.179446","request-headers":{"Accept":"*/*","Accept-Encoding":"gzip, deflate","Connection":"keep-alive","User-Agent":"DLUHC Digital Land"},"resource":"3ba828321bd67edb248db116b22a2d5fae9ab37eb8562be2ff873db45d4be30a","response-headers":{"Accept-Ranges":"bytes","Access-Control-Allow-Origin":"*","Cache-Control":"max-age=300","Connection":"keep-alive","Content-Encoding":"gzip","Content-Length":"18864","Content-Security-Policy":"default-src 'none'; style-src 'unsafe-inline'; sandbox","Content-Type":"text/plain; charset=utf-8","Cross-Origin-Resource-Policy":"cross-origin","Date":"Mon, 26 Jun 2023 00:08:02 GMT","ETag":"W/\"30833b7208f5febd94487448d1760ca3be1a28609536baf4d3b9154baa33a13b\"","Expires":"Mon, 26 Jun 2023 00:13:02 GMT","Source-Age":"0","Strict-Transport-Security":"max-age=31536000","Vary":"Authorization,Accept-Encoding,Origin","Via":"1.1 varnish","X-Cache":"MISS","X-Cache-Hits":"0","X-Content-Type-Options":"nosniff","X-Fastly-Request-ID":"eb037bb5fdd472aef05eb86e86ad74e1bc6f16e5","X-Frame-Options":"deny","X-GitHub-Request-Id":"A7D4:1A50:7E3C88:99CB0F:6498D6E2","X-Served-By":"cache-sjc1000140-SJC","X-Timer":"S1687738083.596795,VS0,VE193","X-XSS-Protection":"1; mode=block"},"ssl-verify":true,"status":"200"}