{"elapsed":"0.216","endpoint-url":"https://www.bracknell-forest.gov.uk/sites/default/files/documents/infrastructure-funding-statement-2019-20.pdf","entry-date":"2021-10-13T00:24:19.859174","request-headers":{"Accept":"*/*","Accept-Encoding":"gzip, deflate","Connection":"keep-alive","User-Agent":"Digital Land"},"resource":"df7d6c16982345d5493a24a24cae035eba88925f11f83c69ecd80e6f760586a7","response-headers":{"Accept-Ranges":"bytes","Age":"86303","Connection":"keep-alive","Content-Length":"795850","Content-Type":"application/pdf","Date":"Tue, 12 Oct 2021 00:27:01 GMT","ETag":"\"60143c41-c24ca\"","Last-Modified":"Fri, 29 Jan 2021 16:48:01 GMT","Server":"nginx","Via":"1.1 4582a1c2d6f2ede6721e6bf1997ded3e.cloudfront.net (CloudFront)","X-Amz-Cf-Id":"hk6fi8v3wK4yedCG2vrGdOvLvT0uTftVXvmYHgV3-KYWhf2zjSedPQ==","X-Amz-Cf-Pop":"IAD66-C1","X-Cache":"Hit from cloudfront","X-Debug-Info":"eyJyZXRyaWVzIjowfQ==","X-Platform-Server":"i-04ca136c4b441e805","X-Request-Id":"00-16ad20e826a3aaa990d84aa3802ba7d1-ca590449cac7680e-00"},"ssl-verify":true,"status":"200"}