{"elapsed":"0.743","endpoint-url":"https://www.barnet.gov.uk/sites/default/files/ifs_report_londonboroughofbarnet_01_04_2019_to_31_03_2020_edited_18_12_2020.pdf","entry-date":"2022-01-08T00:28:36.446657","request-headers":{"Accept":"*/*","Accept-Encoding":"gzip, deflate","Connection":"keep-alive","User-Agent":"DLUHC Digital Land"},"resource":"7563733e346d813effa9d7b9bd1c9ac1c50bd5589630dc539516d4a6515d78c8","response-headers":{"Accept-Ranges":"bytes","Connection":"keep-alive","Content-Length":"347947","Content-Security-Policy":"default-src * data: 'unsafe-eval' 'unsafe-inline'","Content-Type":"application/pdf","Date":"Sat, 08 Jan 2022 00:31:16 GMT","ETag":"\"60e3174b-54f2b\"","Last-Modified":"Mon, 05 Jul 2021 14:29:31 GMT","Referrer-Policy":"no-referrer-when-downgrade","Server":"nginx","Set-Cookie":"visid_incap_2627717=PKofimFRRu+1uz8yLabopVPb2GEAAAAAQUIPAAAAAAAIyp/W5tO+jzn38SyxFpE2; expires=Sat, 07 Jan 2023 06:00:45 GMT; HttpOnly; path=/; Domain=.barnet.gov.uk, nlbi_2627717=gV8cbUn+8TokifLg7t8hkQAAAAATZueCgCHQYT91dLlvwPsp; path=/; Domain=.barnet.gov.uk, incap_ses_1212_2627717=R6oLLFllWSifAqyZD+TREFPb2GEAAAAAABHtfYPofOuuA/y4gYem/g==; path=/; Domain=.barnet.gov.uk","Via":"1.1 b4346add631a498bf6cdbf88cbc5ff12.cloudfront.net (CloudFront)","X-Amz-Cf-Id":"UpjMA1sIviSrZXT_0iitDtAdzwyNCUyUnKo4rk-M9_rZVgPXsq7fUw==","X-Amz-Cf-Pop":"IAD89-C1","X-CDN":"Imperva","X-Cache":"Miss from cloudfront","X-Content-Type-Options":"nosniff","X-Frame-Options":"SAMEORIGIN","X-Iinfo":"6-44083051-44083052 NNNN CT(1 12 0) RT(1641601875593 20) q(0 0 0 1) r(3 3) U12","X-XSS-Protection":"1; mode=block"},"ssl-verify":true,"status":"200"}