{"elapsed":"0.616","endpoint-url":"https://www.hinckley-bosworth.gov.uk/downloads/file/7380/infrastructure_funding_statement_2019_-_2020","entry-date":"2021-12-10T00:27:35.051018","request-headers":{"Accept":"*/*","Accept-Encoding":"gzip, deflate","Connection":"keep-alive","User-Agent":"Digital Land"},"response-headers":{"Cache-Control":"no-store, no-cache, must-revalidate","Connection":"keep-alive","Content-Encoding":"gzip","Content-Length":"5376","Content-Type":"text/html; charset=UTF-8","Date":"Fri, 10 Dec 2021 00:30:37 GMT","Expires":"Thu, 19 Nov 1981 08:52:00 GMT","Node":"jadu-web-1","Pragma":"no-cache","Server":"Web Server","Set-Cookie":"PHPSESSID=I1rkpVJkApdZ5bFnWKju0WvZyb-ndkdwXv81Gsgxf3oCj-MYy3B%2Cs4JmAqz9nJE1; path=/; secure; HttpOnly, TestCookie=Test; path=/; domain=www.hinckley-bosworth.gov.uk; secure; HttpOnly","Strict-Transport-Security":"max-age=2592000","Vary":"Accept-Encoding","X-Content-Type-Options":"nosniff","X-Frame-Options":"SAMEORIGIN","X-UA-Compatible":"IE=edge","X-XSS-Protection":"1; mode=block"},"ssl-verify":true,"status":"200"}