{"elapsed":"8.897","endpoint-url":"https://www.leeds.gov.uk/planning/community-infrastructure-levy/infrastructure-funding-statement","entry-date":"2023-03-23T00:07:02.725889","request-headers":{"Accept":"*/*","Accept-Encoding":"gzip, deflate","Connection":"keep-alive","User-Agent":"DLUHC Digital Land"},"response-headers":{"Connection":"close","Content-Length":"100","Date":"Thu, 23 Mar 2023 00:15:31 GMT","SPRequestGuid":"efdfa1a0-be11-70f0-c578-5ac3855bf4b7","Set-Cookie":"visid_incap_2048550=SE2W5S8/Sz2H8ikcoC6YoxqaG2QAAAAAQUIPAAAAAAA8DJQCKQKKF45UveO3nSQQ; expires=Thu, 21 Mar 2024 06:19:46 GMT; HttpOnly; path=/; Domain=.leeds.gov.uk, incap_ses_1307_2048550=Zi65D8ri3Hq1uFc3RGYjEiOaG2QAAAAAzkxu1vZv+nGUy+McE/UVBg==; path=/; Domain=.leeds.gov.uk","Strict-Transport-Security":"max-age=15552000; includeSubDomains; preload","X-CDN":"Imperva","X-Content-Type-Options":"nosniff","X-Iinfo":"12-24769200-24769214 NNNN CT(92 210 0) RT(1679530522305 70) q(0 0 3 0) r(88 88) U11","X-MS-InvokeApp":"1; RequireReadOnly","X-SharePointHealthScore":"0","request-id":"efdfa1a0-be11-70f0-c578-5ac3855bf4b7"},"ssl-verify":true,"status":"404"}