{"elapsed":"1.258","endpoint-url":"https://www.leicestershire.gov.uk/sites/default/files/field/pdf/2021/2/3/LCC_Infrastructure_Funding_Statement_2019-2020%20FINAL.pdf","entry-date":"2024-01-10T00:07:49.460220","request-headers":{"Accept":"*/*","Accept-Encoding":"gzip, deflate","Connection":"keep-alive","User-Agent":"DLUHC Digital Land"},"resource":"07d19622d1bc1dadbfc2036b04f62eb5645fcacb8c8cee96f661097ff5fd837f","response-headers":{"Accept-Ranges":"bytes","Age":"86399","Cache-Control":"max-age=1209600","Connection":"keep-alive","Content-Length":"2150513","Content-Type":"application/pdf","Date":"Wed, 10 Jan 2024 00:12:17 GMT","Expires":"Tue, 23 Jan 2024 00:12:17 GMT","Last-Modified":"Sat, 16 Jul 2022 17:23:40 GMT","Server":"nginx","Vary":"Host","Via":"varnish","X-AH-Environment":"prod","X-Cache":"HIT","X-Cache-Hits":"3","X-Content-Type-Options":"nosniff","X-Request-ID":"v-bfdd47c6-ae83-11ee-9529-4f06cc3dc7c0"},"ssl-verify":true,"status":"200"}