{"elapsed":"0.697","endpoint-url":"https://www.havant.gov.uk/s106-annual-monitoring-report-2017-pdf-137-kb","entry-date":"2022-01-07T00:29:48.421529","request-headers":{"Accept":"*/*","Accept-Encoding":"gzip, deflate","Connection":"keep-alive","User-Agent":"DLUHC Digital Land"},"resource":"6467dcf7a44b60195b087d48161852b1491178ba44d09c1dc40130162c68a4f1","response-headers":{"Accept-Ranges":"bytes","Connection":"keep-alive","Content-Length":"140412","Content-Type":"application/pdf","Date":"Fri, 07 Jan 2022 00:34:37 GMT","ETag":"\"2a7ca92fd3a0aa9ac475a0ee04d2f4ee\"","Last-Modified":"Mon, 14 Dec 2020 08:41:34 GMT","Server":"AmazonS3","Via":"1.1 6886c621d4716e156349149ba8d65b41.cloudfront.net (CloudFront)","X-Amz-Cf-Id":"3u66GOQeaXdei61f5VAwaZgDHvnc-QgWwEAzYlHVbPTGbx5joWWDyA==","X-Amz-Cf-Pop":"EWR53-C3","X-Cache":"RefreshHit from cloudfront"},"ssl-verify":true,"status":"200"}