{"elapsed":"0.232","endpoint-url":"https://assets.ctfassets.net/knkzaf64jx5x/1Cs2QGhxfhitEJ14P9Ibi7/601a009d82acecc769b28a5a8d2e088c/Essex_County_Council_Infrastructure_Funding_Statement_19_20.pdf","entry-date":"2023-05-29T00:05:31.105861","request-headers":{"Accept":"*/*","Accept-Encoding":"gzip, deflate","Connection":"keep-alive","User-Agent":"DLUHC Digital Land"},"response-headers":{"Cache-Control":"max-age=300","Connection":"keep-alive","Content-Length":"109","Content-Type":"application/json","Date":"Mon, 29 May 2023 00:05:34 GMT","Server":"CloudFront","Via":"1.1 17eb4ce9c34597b3328325a19f8138fe.cloudfront.net (CloudFront)","X-Amz-Cf-Id":"glMmw25DKQzbt10dW3S9h-2DSgc3xIZ9go1-aHaA0VswVW6QW3urVA==","X-Amz-Cf-Pop":"JFK50-P6","X-Cache":"Miss from cloudfront"},"ssl-verify":true,"status":"404"}