{"elapsed":"5.749","endpoint-url":"https://www.dudley.gov.uk/media/16877/dudley-infrastructure-funding-statement-2020-adopted.pdf","entry-date":"2022-08-05T00:06:36.869739","request-headers":{"Accept":"*/*","Accept-Encoding":"gzip, deflate","Connection":"keep-alive","User-Agent":"DLUHC Digital Land"},"resource":"c652fac55b6910644c8856da5b3f294d9358ae5753e14d878952dce53b9e0ef8","response-headers":{"Accept-Ranges":"bytes","Content-Length":"749683","Content-Type":"application/pdf","Date":"Fri, 05 Aug 2022 00:08:41 GMT","ETag":"\"aa53831b2fd5d61:0\"","Last-Modified":"Fri, 18 Dec 2020 11:15:35 GMT","Set-Cookie":"TS015c65a0=0104e7c062a685bdb4b04f778e18f7ba872d1ec6d98cca552e3cc960cd62d5647b718f71031db020fe14ace046e08961d7789c5f57; Path=/; Domain=.www.dudley.gov.uk; Secure; HTTPOnly"},"ssl-verify":true,"status":"200"}