{"bytes":664720,"elapsed":"1.286","endpoint-url":"https://beta.bathnes.gov.uk/sites/default/files/2020-12/infrastructure_funding_statement_2019_2020_0.pdf","entry-date":"2021-11-13T00:24:09.462366","request-headers":{"Accept":"*/*","Accept-Encoding":"gzip, deflate","Connection":"keep-alive","User-Agent":"Digital Land"},"resource":"6b21367609b1e5313eef2e88d1d70c7ac28c33b29c75844961d7899e95c19869","response-headers":{"Accept-Ranges":"bytes","Connection":"keep-alive","Content-Length":"664720","Content-Type":"application/pdf","Date":"Sat, 13 Nov 2021 00:24:14 GMT","ETag":"\"5fe09bec-a2490\"","Last-Modified":"Mon, 21 Dec 2020 12:58:20 GMT","Server":"openresty/1.15.8.1"},"ssl-verify":true,"status":"200"}