{"elapsed":"0.938","endpoint-url":"https://www.northyorkmoors.org.uk/planning/framework/annual-monitoring-reports/NYMoors-AMR-2020-21_final.pdf","entry-date":"2023-12-12T00:05:57.477974","request-headers":{"Accept":"*/*","Accept-Encoding":"gzip, deflate","Connection":"keep-alive","User-Agent":"DLUHC Digital Land"},"response-headers":{"Cache-Control":"private, max-age=0","Connection":"keep-alive","Content-Encoding":"gzip","Content-Type":"text/html; charset=utf-8","Date":"Tue, 12 Dec 2023 00:13:46 GMT","Expires":"Tue, 12 Dec 2023 00:43:45 GMT","Pragma":"cache","Server":"openresty","Set-Cookie":"SQ_SYSTEM_SESSION=775e8fb608a53ebf3f1a690652080b25; path=/; secure; HttpOnly","Transfer-Encoding":"chunked","Vary":"Accept-Encoding, Accept-Encoding","Via":"1.1 np2-web01.ash2.squiz.cloud","X-Cache":"MISS from np2-web01.ash2.squiz.cloud","X-Content-Type-Options":"nosniff","X-Frame-Options":"SAMEORIGIN","X-Request-ID":"7bc9dca0-0129-41b4-a59d-c2cbaf8ef24c","X-upgrade-enabled":"off"},"ssl-verify":true,"status":"404"}