{"elapsed":"0.693","endpoint-url":"https://www.knowsley.gov.uk/knowsleycouncil/media/Documents/S106-Infrastructure-Funding-Statement-2019-20.pdf","entry-date":"2023-11-25T00:05:36.159659","request-headers":{"Accept":"*/*","Accept-Encoding":"gzip, deflate","Connection":"keep-alive","User-Agent":"DLUHC Digital Land"},"response-headers":{"CF-Cache-Status":"MISS","CF-RAY":"82b5aaec8c0b2a24-ORD","Cache-Control":"max-age=14400","Connection":"keep-alive","Content-Encoding":"gzip","Content-Type":"text/html","Date":"Sat, 25 Nov 2023 00:10:16 GMT","Server":"cloudflare","Set-Cookie":"__cf_bm=60asjGI1dSFUT7c50hd9bnyoJnUgtWlPvswEO1c4tk8-1700871016-0-AR7YO2mkw7IOSpFqJSdz1XoMSJ0Qaz1XPYX8Yez2mjsVRfunYeZVK3Q/TJS8Pbg7uHWTTafaY4kHhHX8mmyHpY4=; path=/; expires=Sat, 25-Nov-23 00:40:16 GMT; domain=.knowsley.gov.uk; HttpOnly; Secure; SameSite=None","Transfer-Encoding":"chunked","Vary":"Accept-Encoding","x-powered-by":"ASP.NET"},"ssl-verify":true,"status":"404"}