{"elapsed":"0.41","endpoint-url":"https://cdn.havant.gov.uk/public/documents/AMR%202018%20(CIL).pdf","entry-date":"2022-06-16T00:05:40.939096","request-headers":{"Accept":"*/*","Accept-Encoding":"gzip, deflate","Connection":"keep-alive","User-Agent":"DLUHC Digital Land"},"resource":"0b2e3a24d7afaf246af59140acf3a6b6dd251bf7492e7ac6a97a6752da51c0af","response-headers":{"Accept-Ranges":"bytes","Connection":"keep-alive","Content-Length":"20264","Content-Type":"application/pdf","Date":"Thu, 16 Jun 2022 00:06:12 GMT","ETag":"\"1eaac4ee019000031abfb8aec76e1ebe\"","Last-Modified":"Mon, 14 Dec 2020 08:41:34 GMT","Server":"AmazonS3","Via":"1.1 ec8a0c87d9c8db72809715cc06430ab8.cloudfront.net (CloudFront)","X-Amz-Cf-Id":"DhK5BUaWNaZqhrDuprpIl8z8uHOk1R-57baxqY-6jf-34ks42nhF5g==","X-Amz-Cf-Pop":"DFW55-C2","X-Cache":"RefreshHit from cloudfront"},"ssl-verify":true,"status":"200"}