{"elapsed":"0.948","endpoint-url":"https://www.eastcambs.gov.uk/sites/default/files/Infrastructure%20Funding%20Statement%202019-2020.pdf","entry-date":"2023-02-19T00:06:59.278034","request-headers":{"Accept":"*/*","Accept-Encoding":"gzip, deflate","Connection":"keep-alive","User-Agent":"DLUHC Digital Land"},"resource":"ef25dc1f8f253195c110e2e8e23f9d1d4124ba792407a13182bae4d8d17f90bd","response-headers":{"Accept-Ranges":"bytes","Age":"0","Connection":"keep-alive","Content-Length":"210004","Content-Type":"application/pdf","Date":"Sun, 19 Feb 2023 00:10:53 GMT","Etag":"\"626ad58a-33454\"","Last-Modified":"Thu, 28 Apr 2022 17:57:30 GMT","Server":"nginx","Strict-Transport-Security":"max-age=300","Via":"1.1 varnish, 1.1 varnish","X-Cache":"MISS, MISS","X-Cache-Hits":"0, 0","X-Pantheon-Styx-Hostname":"styx-fe3fe4-c-b5c48bd8b-k4d9c","X-Served-By":"cache-ams12720-AMS, cache-dfw-kdfw8210120-DFW","X-Styx-Req-Id":"dfeb47c8-afe9-11ed-9ebf-a655d194ce9c","X-Timer":"S1676765454.673600,VS0,VE302"},"ssl-verify":true,"status":"200"}