{"elapsed":"0.757","endpoint-url":"https://cdn.havant.gov.uk/public/documents/2015%20CIL%20Annual%20Monitoring%20.pdf","entry-date":"2022-12-31T00:06:10.050091","request-headers":{"Accept":"*/*","Accept-Encoding":"gzip, deflate","Connection":"keep-alive","User-Agent":"DLUHC Digital Land"},"resource":"e8006695951c762a8dd3cda965618cb5d0909706f88eb5d7635cbc7e86dd20b6","response-headers":{"Accept-Ranges":"bytes","Connection":"keep-alive","Content-Length":"10647","Content-Type":"application/pdf","Date":"Sat, 31 Dec 2022 00:06:21 GMT","ETag":"\"7c7c558b7a35f300e6f90d4557a37128\"","Last-Modified":"Mon, 14 Dec 2020 08:41:34 GMT","Server":"AmazonS3","Via":"1.1 65e185f36e65abff9322e261be3491d4.cloudfront.net (CloudFront)","X-Amz-Cf-Id":"p5YZ-OEzlrQL_AQoNQkHvHepaJGXxOxM7FIFkcLsiTdQI3Prj1FPQQ==","X-Amz-Cf-Pop":"IAD50-C2","X-Cache":"Miss from cloudfront"},"ssl-verify":true,"status":"200"}