{"elapsed":"0.427","endpoint-url":"https://cdn.havant.gov.uk/public/documents/2016%20CIL%20Monitoring.pdf","entry-date":"2023-06-28T00:07:26.802504","request-headers":{"Accept":"*/*","Accept-Encoding":"gzip, deflate","Connection":"keep-alive","User-Agent":"DLUHC Digital Land"},"resource":"d5a142be10893776bf97eebf12be7b7b98037721023ce09b7f4121a4f89a1e65","response-headers":{"Accept-Ranges":"bytes","Connection":"keep-alive","Content-Length":"10213","Content-Type":"application/pdf","Date":"Wed, 28 Jun 2023 00:07:38 GMT","ETag":"\"1a6aadfb2561af0a71f3427b67fc99e4\"","Last-Modified":"Mon, 14 Dec 2020 08:41:34 GMT","Server":"AmazonS3","Via":"1.1 4ae0902ea4e10dc74700d1753a74440a.cloudfront.net (CloudFront)","X-Amz-Cf-Id":"m79i0_Sch_xpQQjkmMNnB8jgqMF88sxWC73ZebbSjI0_3QsyCYLP3A==","X-Amz-Cf-Pop":"IAD55-P3","X-Cache":"Miss from cloudfront"},"ssl-verify":true,"status":"200"}