{"elapsed":"0.222","endpoint-url":"https://assets.ctfassets.net/knkzaf64jx5x/1Cs2QGhxfhitEJ14P9Ibi7/601a009d82acecc769b28a5a8d2e088c/Essex_County_Council_Infrastructure_Funding_Statement_19_20.pdf","entry-date":"2023-02-11T00:06:36.951281","request-headers":{"Accept":"*/*","Accept-Encoding":"gzip, deflate","Connection":"keep-alive","User-Agent":"DLUHC Digital Land"},"response-headers":{"Cache-Control":"max-age=300","Connection":"keep-alive","Content-Length":"109","Content-Type":"application/json","Date":"Sat, 11 Feb 2023 00:06:42 GMT","Server":"CloudFront","Via":"1.1 d32136caad5f6a80e6bec65185c2a290.cloudfront.net (CloudFront)","X-Amz-Cf-Id":"Fi_5bcfDP4XVO_ZimUS51LS_rAE2V947o5_rccx7EbrbjFgAO-mIsg==","X-Amz-Cf-Pop":"SFO5-P2","X-Cache":"GeneratedResponse from cloudfront"},"ssl-verify":true,"status":"404"}